dduk/__init__.py
dduk/__main__.py
dduk/utility/__init__.py
dduk/utility/__main__.py
dduk/utility/ansicode.py
dduk/utility/jsonutility.py
dduk/utility/moduleutility.py
dduk/utility/resourcemanager.py
dduk/utility/strutility.py
dduk/utility/json/__init__.py
dduk/utility/json/__main__.py
dduk/utility/json/collection.py
dduk/utility/json/exporter.py
dduk/utility/json/importer.py
dduk/utility/json/object.py
dduk/utility/logging/__init__.py
dduk/utility/logging/__main__.py
dduk/utility/logging/level.py
dduk/utility/logging/logger.py
dduk_utility-0.0.30.dist-info/LICENSE
dduk_utility-0.0.30.dist-info/METADATA
dduk_utility-0.0.30.dist-info/WHEEL
dduk_utility-0.0.30.dist-info/top_level.txt
dduk_utility-0.0.30.dist-info/RECORD
